simpleotp/__init__.py
simpleotp/otp.py
simple_otp-0.1.1.dist-info/LICENSE
simple_otp-0.1.1.dist-info/METADATA
simple_otp-0.1.1.dist-info/WHEEL
simple_otp-0.1.1.dist-info/top_level.txt
simple_otp-0.1.1.dist-info/RECORD
