Metadata-Version: 2.1
Name: simple-otp
Version: 0.1.1
Summary: A simple OTP Generation and Verification Library which works without a Database or Cache
Home-page: https://github.com/nogoodusername/simple-otp
Author: Kshitij Nagvekar
Author-email: kshitij.nagvekar@workindia.in
License: MIT license
Platform: UNKNOWN
Classifier: Development Status :: 5 - Production/Stable
Classifier: License :: OSI Approved :: MIT License
Classifier: Natural Language :: English
Classifier: Programming Language :: Python :: 3
Classifier: Programming Language :: Python :: 3.6
Classifier: Programming Language :: Python :: 3.7
Classifier: Operating System :: OS Independent
Requires-Python: >=3.6
